colmena/__init__.py
colmena/colmena.cpython-38-x86_64-linux-gnu.so
colmena_ai-0.2.0.dist-info/METADATA
colmena_ai-0.2.0.dist-info/WHEEL
colmena_ai-0.2.0.dist-info/RECORD
